{"2x4 roller derby": [4, "/categories/2x4-roller-derby/"], "argentina": [2, "/categories/argentina/"], "bali": [1, "/categories/bali/"], "bangkok roller derby": [5, "/categories/bangkok-roller-derby/"], "bootcamps": [7, "/categories/bootcamps/"], "cairollers": [3, "/categories/cairollers/"], "china": [2, "/categories/china/"], "crowdfunding": [5, "/categories/crowdfunding/"], "derby without borders": [2, "/categories/derby-without-borders/"], "dubai roller derby": [4, "/categories/dubai-roller-derby/"], "ecuador": [1, "/categories/ecuador/"], "egypt": [1, "/categories/egypt/"], "forajidas roller derby": [1, "/categories/forajidas-roller-derby/"], "hot lava rollers": [1, "/categories/hot-lava-rollers/"], "international roller derby": [101, "/categories/international-roller-derby/"], "russia": [1, "/categories/russia/"], "thailand": [1, "/categories/thailand/"], "uae roller derby all-stars": [2, "/categories/uae-roller-derby-all-stars/"], "dundee": [13, "/categories/dundee/"], "dundee roller derby": [6, "/categories/dundee-roller-derby/"], "international derby": [157, "/categories/international-derby/"], "wftda": [22, "/categories/wftda/"], "arrg": [63, "/categories/arrg/"], "home season tournament": [29, "/categories/home-season-tournament/"], "leithal weapons": [15, "/categories/leithal-weapons/"], "skatefast club": [12, "/categories/skatefast-club/"], "upcoming bouts": [336, "/categories/upcoming-bouts/"], "articles": [454, "/categories/articles/"], "belfast roller derby": [3, "/categories/belfast-roller-derby/"], "in the news": [42, "/categories/in-the-news/"], "power jam": [1, "/categories/power-jam/"], "video games": [1, "/categories/video-games/"], "an interview with...": [71, "/categories/an-interview-with/"], "nasty nessies roller girls": [15, "/categories/nasty-nessies-roller-girls/"], "nnrg": [17, "/categories/nnrg/"], "capital city roller derby": [22, "/categories/capital-city-roller-derby/"], "fresh meat": [41, "/categories/fresh-meat/"], "men's roller derby": [78, "/categories/mens-roller-derby/"], "merby": [4, "/categories/merby/"], "team scotland": [45, "/categories/team-scotland/"], "bairn city rollers": [34, "/categories/bairn-city-rollers/"], "co-ed roller derby": [6, "/categories/co-ed-roller-derby/"], "image": [3, "/categories/image/"], "mean city roller derby": [25, "/categories/mean-city-roller-derby/"], "roller derby": [12, "/categories/roller-derby/"], "the jakey bites": [14, "/categories/the-jakey-bites/"], "the skelpies": [7, "/categories/the-skelpies/"], "the tayminators": [2, "/categories/the-tayminators/"], "fierce valley roller girls": [72, "/categories/fierce-valley-roller-girls/"], "fvrg": [65, "/categories/fvrg/"], "interviews": [229, "/categories/interviews/"], "monthly diary": [38, "/categories/monthly-diary/"], "ddrd": [4, "/categories/ddrd/"], "deadly divas roller derby": [4, "/categories/deadly-divas-roller-derby/"], "parma violents": [8, "/categories/parma-violents/"], "one year later": [4, "/categories/one-year-later/"], "fvrc": [17, "/categories/fvrc/"], "junior derby": [12, "/categories/junior-derby/"], "junior roller derby": [27, "/categories/junior-roller-derby/"], "central belters": [10, "/categories/central-belters/"], "lothian derby dolls": [23, "/categories/lothian-derby-dolls/"], "auld reekie roller girls": [38, "/categories/auld-reekie-roller-girls/"], "ecdx": [5, "/categories/ecdx/"], "fundraiser event": [31, "/categories/fundraiser-event/"], "fundraising events": [52, "/categories/fundraising-events/"], "glasgow roller derby": [41, "/categories/glasgow-roller-derby/"], "grd": [56, "/categories/grd/"], "irn bruisers": [18, "/categories/irn-bruisers/"], "twisted thistles": [13, "/categories/twisted-thistles/"], "bout reports": [39, "/categories/bout-reports/"], "gcrg": [37, "/categories/gcrg/"], "granite city roller girls": [27, "/categories/granite-city-roller-girls/"], "maiden grrders": [16, "/categories/maiden-grrders/"], "northern fights": [4, "/categories/northern-fights/"], "dundee roller girls": [50, "/categories/dundee-roller-girls/"], "quiz": [2, "/categories/quiz/"], "newsletter": [1, "/categories/newsletter/"], "roller derby bootcamps": [16, "/categories/roller-derby-bootcamps/"], "aberdeen": [11, "/categories/aberdeen/"], "double header": [4, "/categories/double-header/"], "jakey bites": [7, "/categories/jakey-bites/"], "silvery tayzers": [16, "/categories/silvery-tayzers/"], "annoucements": [39, "/categories/annoucements/"], "ref's corner": [2, "/categories/refs-corner/"], "cherry bombers": [13, "/categories/cherry-bombers/"], "drg": [30, "/categories/drg/"], "roller derby world cup 2011": [41, "/categories/roller-derby-world-cup-2011/"], "team scotland roller derby": [15, "/categories/team-scotland-roller-derby/"], "tryouts": [1, "/categories/tryouts/"], "ukrda": [17, "/categories/ukrda/"], "announcers": [3, "/categories/announcers/"], "newcastle roller girls": [17, "/categories/newcastle-roller-girls/"], "craft fayre": [3, "/categories/craft-fayre/"], "falkirk": [6, "/categories/falkirk/"], "grangemouth sports complex": [10, "/categories/grangemouth-sports-complex/"], "competition": [4, "/categories/competition/"], "merchandise": [3, "/categories/merchandise/"], "into the nitemare": [2, "/categories/into-the-nitemare/"], "disc": [1, "/categories/disc/"], "barrow infernos": [1, "/categories/barrow-infernos/"], "meadowbank sports centre": [2, "/categories/meadowbank-sports-centre/"], "sur5al": [7, "/categories/sur5al/"], "beach leisure centre": [1, "/categories/beach-leisure-centre/"], "oslo roller derby": [1, "/categories/oslo-roller-derby/"], "stirling": [3, "/categories/stirling/"], "the peak": [3, "/categories/the-peak/"], "firecrackers": [1, "/categories/firecrackers/"], "inferno": [1, "/categories/inferno/"], "skelpies": [8, "/categories/skelpies/"], "merdc": [1, "/categories/merdc/"], "campus": [1, "/categories/campus/"], "cathouse": [1, "/categories/cathouse/"], "glasgow": [4, "/categories/glasgow/"], "new town colliders": [1, "/categories/new-town-colliders/"], "new town roller girls": [14, "/categories/new-town-roller-girls/"], "2014 blood & thunder roller derby world cup": [40, "/categories/2014-blood-thunder-roller-derby-world-cup/"], "ldd": [11, "/categories/ldd/"], "bout report": [18, "/categories/bout-report/"], "quad nations": [1, "/categories/quad-nations/"], "tournament": [77, "/categories/tournament/"], "tenerife": [2, "/categories/tenerife/"], "grangemouth": [6, "/categories/grangemouth/"], "hades roller boys": [5, "/categories/hades-roller-boys/"], "men behaving derby": [3, "/categories/men-behaving-derby/"], "team nitemare": [3, "/categories/team-nitemare/"], "the jakey tayzers": [1, "/categories/the-jakey-tayzers/"], "ntrg": [9, "/categories/ntrg/"], "bad omens": [9, "/categories/bad-omens/"], "death stars": [10, "/categories/death-stars/"], "hell's belles": [10, "/categories/hells-belles/"], "home teams": [6, "/categories/home-teams/"], "tyrannosaurus wrecks": [1, "/categories/tyrannosaurus-wrecks/"], "granite city brawlermen": [10, "/categories/granite-city-brawlermen/"], "men's derby": [3, "/categories/mens-derby/"], "north wales roller derby": [1, "/categories/north-wales-roller-derby/"], "tyne and fear": [4, "/categories/tyne-and-fear/"], "ddrg": [1, "/categories/ddrg/"], "adverts": [1, "/categories/adverts/"], "coaches": [4, "/categories/coaches/"], "skating": [1, "/categories/skating/"], "fierce valley roller cubs": [17, "/categories/fierce-valley-roller-cubs/"], "pictures": [20, "/categories/pictures/"], "xmas": [1, "/categories/xmas/"], "lead jammer": [1, "/categories/lead-jammer/"], "print media": [1, "/categories/print-media/"], "video": [22, "/categories/video/"], "mrdwc 2014": [1, "/categories/mrdwc-2014/"], "men's roller derby world cup": [15, "/categories/mens-roller-derby-world-cup/"], "power of scotland": [16, "/categories/power-of-scotland/"], "preston roller girls": [5, "/categories/preston-roller-girls/"], "mcrd": [3, "/categories/mcrd/"], "the arc": [2, "/categories/the-arc/"], "international": [10, "/categories/international/"], "kokeshi roller dolls": [5, "/categories/kokeshi-roller-dolls/"], "krd": [1, "/categories/krd/"], "the big o": [3, "/categories/the-big-o/"], "news": [3, "/categories/news/"], "cannon belles": [10, "/categories/cannon-belles/"], "canny belters": [1, "/categories/canny-belters/"], "nrg": [1, "/categories/nrg/"], "whippin hinnies": [4, "/categories/whippin-hinnies/"], "voodoo roller dollies": [7, "/categories/voodoo-roller-dollies/"], "roller derby world cup": [62, "/categories/roller-derby-world-cup/"], "southern discomfort": [3, "/categories/southern-discomfort/"], "spring roll": [1, "/categories/spring-roll/"], "timetable": [1, "/categories/timetable/"], "podcasts": [1, "/categories/podcasts/"], "made": [1, "/categories/made/"], "made in scotland": [1, "/categories/made-in-scotland/"], "usars": [1, "/categories/usars/"], "ayrshire roller derby": [9, "/categories/ayrshire-roller-derby/"], "derby review 2014": [4, "/categories/derby-review-2014/"], "doonhame derby dolls": [7, "/categories/doonhame-derby-dolls/"], "fair city rollers": [13, "/categories/fair-city-rollers/"], "inverness city roller derby": [8, "/categories/inverness-city-roller-derby/"], "renfrewshire rockin' rollers": [1, "/categories/renfrewshire-rockin-rollers/"], "shetland roller derby": [3, "/categories/shetland-roller-derby/"], "battle of britain roller derby tournament": [1, "/categories/battle-of-britain-roller-derby-tournament/"], "edinburgh": [4, "/categories/edinburgh/"], "roller derby world cup 2014": [49, "/categories/roller-derby-world-cup-2014/"], "team canada": [3, "/categories/team-canada/"], "team mexico": [2, "/categories/team-mexico/"], "team puerto rico": [3, "/categories/team-puerto-rico/"], "team usa": [2, "/categories/team-usa/"], "future derby": [6, "/categories/future-derby/"], "future of derby": [4, "/categories/future-of-derby/"], "team argentina": [3, "/categories/team-argentina/"], "toxic lima roller derby": [1, "/categories/toxic-lima-roller-derby/"], "world derby": [1, "/categories/world-derby/"], "timings": [1, "/categories/timings/"], "middle east": [1, "/categories/middle-east/"], "roller derby beirut": [1, "/categories/roller-derby-beirut/"], "prague roller derby": [1, "/categories/prague-roller-derby/"], "white night furies": [4, "/categories/white-night-furies/"], "blood and thunder world cup 2014": [13, "/categories/blood-and-thunder-world-cup-2014/"], "tournaments": [25, "/categories/tournaments/"], "team switzerland": [2, "/categories/team-switzerland/"], "team france": [3, "/categories/team-france/"], "ukroc": [1, "/categories/ukroc/"], "team england": [3, "/categories/team-england/"], "team ireland": [6, "/categories/team-ireland/"], "team wales": [9, "/categories/team-wales/"], "bristol roller derby": [1, "/categories/bristol-roller-derby/"], "capital city": [13, "/categories/capital-city/"], "htm hell": [1, "/categories/htm-hell/"], "vice quads": [1, "/categories/vice-quads/"], "team denmark": [2, "/categories/team-denmark/"], "team finland": [2, "/categories/team-finland/"], "team norway": [2, "/categories/team-norway/"], "team sweden": [5, "/categories/team-sweden/"], "team chile": [2, "/categories/team-chile/"], "team brasil": [2, "/categories/team-brasil/"], "team colombia": [2, "/categories/team-colombia/"], "team germany": [3, "/categories/team-germany/"], "team belgium": [3, "/categories/team-belgium/"], "team netherlands": [2, "/categories/team-netherlands/"], "blackpool roller derby": [3, "/categories/blackpool-roller-derby/"], "furness firecrackers": [2, "/categories/furness-firecrackers/"], "team crazy legs": [2, "/categories/team-crazy-legs/"], "crowd funder": [1, "/categories/crowd-funder/"], "inerview with tequila jammer": [1, "/categories/inerview-with-tequila-jammer/"], "mens roller derby scotland": [5, "/categories/mens-roller-derby-scotland/"], "tequila jammer": [1, "/categories/tequila-jammer/"], "euro stars": [1, "/categories/euro-stars/"], "hallglen sports centre": [1, "/categories/hallglen-sports-centre/"], "jack kane centre": [1, "/categories/jack-kane-centre/"], "durham roller derby": [2, "/categories/durham-roller-derby/"], "rising stars": [2, "/categories/rising-stars/"], "cannie gingers": [4, "/categories/cannie-gingers/"], "cherry poppers": [2, "/categories/cherry-poppers/"], "coed": [4, "/categories/coed/"], "critical hit": [1, "/categories/critical-hit/"], "niko blocker gorey": [1, "/categories/niko-blocker-gorey/"], "intraleague": [2, "/categories/intraleague/"], "team australia": [2, "/categories/team-australia/"], "team south africa": [3, "/categories/team-south-africa/"], "team za": [1, "/categories/team-za/"], "team greece": [2, "/categories/team-greece/"], "team italy": [2, "/categories/team-italy/"], "team portugal": [2, "/categories/team-portugal/"], "team spain": [3, "/categories/team-spain/"], "capital citys new skater intake": [2, "/categories/capital-citys-new-skater-intake/"], "ccrd": [4, "/categories/ccrd/"], "third fresh meat": [1, "/categories/third-fresh-meat/"], "london rockin rollers": [2, "/categories/london-rockin-rollers/"], "team west indies": [3, "/categories/team-west-indies/"], "derby news network": [1, "/categories/derby-news-network/"], "dnn": [2, "/categories/dnn/"], "team new zealand": [2, "/categories/team-new-zealand/"], "2011 blood & thunder roller derby world cup": [4, "/categories/2011-blood-thunder-roller-derby-world-cup/"], "interleagues": [1, "/categories/interleagues/"], "hamburg harbor girls": [1, "/categories/hamburg-harbor-girls/"], "team japan": [3, "/categories/team-japan/"], "world cup": [1, "/categories/world-cup/"], "batter c power": [1, "/categories/batter-c-power/"], "bcr": [12, "/categories/bcr/"], "canny gingers": [1, "/categories/canny-gingers/"], "london rollergirls": [5, "/categories/london-rollergirls/"], "lrg": [1, "/categories/lrg/"], "middlesbrough milk rollers": [3, "/categories/middlesbrough-milk-rollers/"], "mmr": [2, "/categories/mmr/"], "first bout": [1, "/categories/first-bout/"], "fundraising": [5, "/categories/fundraising/"], "men's roller derby edinburgh": [2, "/categories/mens-roller-derby-edinburgh/"], "wirral pack animals": [1, "/categories/wirral-pack-animals/"], "murderdrome": [1, "/categories/murderdrome/"], "bout preview": [2, "/categories/bout-preview/"], "roller derby bootcamp": [6, "/categories/roller-derby-bootcamp/"], "royal windsor rollergirls": [2, "/categories/royal-windsor-rollergirls/"], "jammin' dodgers": [1, "/categories/jammin-dodgers/"], "jutes of hazzard": [1, "/categories/jutes-of-hazzard/"], "press gangsters": [1, "/categories/press-gangsters/"], "gcb": [1, "/categories/gcb/"], "belter skelpers": [1, "/categories/belter-skelpers/"], "review of the year": [20, "/categories/review-of-the-year/"], "review": [3, "/categories/review/"], "taster session": [3, "/categories/taster-session/"], "facebook": [1, "/categories/facebook/"], "arc": [1, "/categories/arc/"], "statistics": [25, "/categories/statistics/"], "2014 in review": [4, "/categories/2014-in-review/"], "new faces of derby": [1, "/categories/new-faces-of-derby/"], "new skaters": [1, "/categories/new-skaters/"], "scottish mens roller derby": [9, "/categories/scottish-mens-roller-derby/"], "grizabelta": [1, "/categories/grizabelta/"], "mighty unicrons": [2, "/categories/mighty-unicrons/"], "scottish men's roller derby nationals": [5, "/categories/scottish-mens-roller-derby-nationals/"], "smrdn": [5, "/categories/smrdn/"], "british roller derby championships": [112, "/categories/british-roller-derby-championships/"], "men's roller derby falkirk": [1, "/categories/mens-roller-derby-falkirk/"], "tyne & fear": [3, "/categories/tyne-fear/"], "all star reserves": [2, "/categories/all-star-reserves/"], "gotham girls roller derby": [1, "/categories/gotham-girls-roller-derby/"], "rose city rollers": [1, "/categories/rose-city-rollers/"], "victorian roller derby league": [2, "/categories/victorian-roller-derby-league/"], "wftda championships": [2, "/categories/wftda-championships/"], "4nations": [1, "/categories/4nations/"], "roller derby world cup calgary 2016": [3, "/categories/roller-derby-world-cup-calgary-2016/"], "super smash brollers": [3, "/categories/super-smash-brollers/"], "vegan": [1, "/categories/vegan/"], "vegfest": [1, "/categories/vegfest/"], "home season": [3, "/categories/home-season/"], "t-wrecks": [1, "/categories/t-wrecks/"], "hellveticats": [1, "/categories/hellveticats/"], "mighty unicorns": [3, "/categories/mighty-unicorns/"], "british championship": [8, "/categories/british-championship/"], "deaf and hard of hearing": [1, "/categories/deaf-and-hard-of-hearing/"], "chaos engine": [1, "/categories/chaos-engine/"], "new wheeled order": [2, "/categories/new-wheeled-order/"], "unicorns": [1, "/categories/unicorns/"], "helgin roller derby": [5, "/categories/helgin-roller-derby/"], "hrd": [1, "/categories/hrd/"], "birthday": [1, "/categories/birthday/"], "beijing": [1, "/categories/beijing/"], "beijing roller derby": [3, "/categories/beijing-roller-derby/"], "hong kong": [1, "/categories/hong-kong/"], "hong kong roller derby": [3, "/categories/hong-kong-roller-derby/"], "shang-hai rollers": [3, "/categories/shang-hai-rollers/"], "shanghai": [1, "/categories/shanghai/"], "timetables": [1, "/categories/timetables/"], "wftda division 1 playoffs": [3, "/categories/wftda-division-1-playoffs/"], "new bouters": [1, "/categories/new-bouters/"], "scottish derby": [1, "/categories/scottish-derby/"], "scottish men's derby": [1, "/categories/scottish-mens-derby/"], "analytics": [2, "/categories/analytics/"], "flat track stats": [8, "/categories/flat-track-stats/"], "fts": [1, "/categories/fts/"], "auldreekierollergirls": [2, "/categories/auldreekierollergirls/"], "b-teams": [1, "/categories/b-teams/"], "fight hawks": [6, "/categories/fight-hawks/"], "scottish men's roller derby league": [1, "/categories/scottish-mens-roller-derby-league/"], "wcrd": [1, "/categories/wcrd/"], "wee county roller derby": [2, "/categories/wee-county-roller-derby/"], "analysis": [3, "/categories/analysis/"], "flattrackstats": [2, "/categories/flattrackstats/"], "books": [1, "/categories/books/"], "derby life": [1, "/categories/derby-life/"], "reviews": [6, "/categories/reviews/"], "scotland": [2, "/categories/scotland/"], "gcrd": [4, "/categories/gcrd/"], "granite city roller derby": [16, "/categories/granite-city-roller-derby/"], "2015": [1, "/categories/2015/"], "fcr": [11, "/categories/fcr/"], "logo competition": [1, "/categories/logo-competition/"], "jrda": [3, "/categories/jrda/"], "malmo crime city rollers": [4, "/categories/malmo-crime-city-rollers/"], "manchester roller derby": [3, "/categories/manchester-roller-derby/"], "severn roller torrent": [1, "/categories/severn-roller-torrent/"], "brim stone": [1, "/categories/brim-stone/"], "bint imperial": [1, "/categories/bint-imperial/"], "national museum of roller derby": [2, "/categories/national-museum-of-roller-derby/"], "wirral whipiteres": [1, "/categories/wirral-whipiteres/"], "nso": [4, "/categories/nso/"], "grg": [22, "/categories/grg/"], "nmrd": [1, "/categories/nmrd/"], "roller derby shop": [1, "/categories/roller-derby-shop/"], "nasty nessies": [1, "/categories/nasty-nessies/"], "norfolk brawds": [1, "/categories/norfolk-brawds/"], "tiger bay brawlers": [5, "/categories/tiger-bay-brawlers/"], "york minxters": [4, "/categories/york-minxters/"], "fear maidens": [6, "/categories/fear-maidens/"], "wakey wheeled cats": [1, "/categories/wakey-wheeled-cats/"], "officials": [2, "/categories/officials/"], "referees": [4, "/categories/referees/"], "glasgow slayers": [1, "/categories/glasgow-slayers/"], "the inhuman league": [1, "/categories/the-inhuman-league/"], "derby revolution": [1, "/categories/derby-revolution/"], "roller grrrls": [1, "/categories/roller-grrrls/"], "euroderby": [2, "/categories/euroderby/"], "srd": [1, "/categories/srd/"], "glasgow roller girls": [1, "/categories/glasgow-roller-girls/"], "team iran roller derby": [2, "/categories/team-iran-roller-derby/"], "upcoming events": [86, "/categories/upcoming-events/"], "latin american derby": [8, "/categories/latin-american-derby/"], "officiating clinics": [1, "/categories/officiating-clinics/"], "violentango": [3, "/categories/violentango/"], "wftda recognised tournaments": [3, "/categories/wftda-recognised-tournaments/"], "a chat with...": [18, "/categories/a-chat-with/"], "wftda apprenticeship": [1, "/categories/wftda-apprenticeship/"], "euroclash": [15, "/categories/euroclash/"], "paris rollergirls": [2, "/categories/paris-rollergirls/"], "team wrdj": [1, "/categories/team-wrdj/"], "tomodachi derby tournament": [11, "/categories/tomodachi-derby-tournament/"], "women's roller derby japan": [2, "/categories/womens-roller-derby-japan/"], "\u65e5\u672c\u8a9e": [1, "/categories/ri-ben-yu/"], "lado oscuro roller derby": [1, "/categories/lado-oscuro-roller-derby/"], "quad wars": [1, "/categories/quad-wars/"], "doonhame roller derby": [2, "/categories/doonhame-roller-derby/"], "rule56": [5, "/categories/rule56/"], "webinar": [1, "/categories/webinar/"], "okinawa roller derby": [1, "/categories/okinawa-roller-derby/"], "finnish derby": [1, "/categories/finnish-derby/"], "pohjola cup": [2, "/categories/pohjola-cup/"], "team russia": [3, "/categories/team-russia/"], "ninjapan rollers": [2, "/categories/ninjapan-rollers/"], "late n' lite": [2, "/categories/late-n-lite/"], "officials bootcamp": [2, "/categories/officials-bootcamp/"], "leeds roller derby": [7, "/categories/leeds-roller-derby/"], "glasgow men's roller derby": [5, "/categories/glasgow-mens-roller-derby/"], "all-gender roller derby": [7, "/categories/all-gender-roller-derby/"], "chile": [3, "/categories/chile/"], "short format tournaments": [2, "/categories/short-format-tournaments/"], "torneo brutal": [1, "/categories/torneo-brutal/"], "dirty river roller derby": [1, "/categories/dirty-river-roller-derby/"], "go-go gent roller derby": [2, "/categories/go-go-gent-roller-derby/"], "nantes derby girls": [1, "/categories/nantes-derby-girls/"], "one love roller dolls": [1, "/categories/one-love-roller-dolls/"], "west track story": [1, "/categories/west-track-story/"], "new national teams": [2, "/categories/new-national-teams/"], "roller derby world cup 2018": [5, "/categories/roller-derby-world-cup-2018/"], "team austria": [1, "/categories/team-austria/"], "coaching": [6, "/categories/coaching/"], "orkney viqueens": [3, "/categories/orkney-viqueens/"], "smarty pants": [2, "/categories/smarty-pants/"], "announcements": [5, "/categories/announcements/"], "scottish roller derby": [4, "/categories/scottish-roller-derby/"], "team romania": [1, "/categories/team-romania/"], "british champs": [5, "/categories/british-champs/"], "champs": [1, "/categories/champs/"], "gmrd": [1, "/categories/gmrd/"], "teeside skate invaders": [3, "/categories/teeside-skate-invaders/"], "dublin roller derby": [7, "/categories/dublin-roller-derby/"], "devil dog derby dames": [3, "/categories/devil-dog-derby-dames/"], "central city rollergirls": [4, "/categories/central-city-rollergirls/"], "bear city roller derby": [3, "/categories/bear-city-roller-derby/"], "pan-asian spring rollers": [6, "/categories/pan-asian-spring-rollers/"], "tokyo roller girls": [3, "/categories/tokyo-roller-girls/"], "yokosuka sushi rollers": [2, "/categories/yokosuka-sushi-rollers/"], "hot wheel roller derby": [2, "/categories/hot-wheel-roller-derby/"], "leeds roller dolls": [3, "/categories/leeds-roller-dolls/"], "fairbanks rollergirls": [2, "/categories/fairbanks-rollergirls/"], "durham rolling angels": [1, "/categories/durham-rolling-angels/"], "bonnie colliders": [6, "/categories/bonnie-colliders/"], "captains": [1, "/categories/captains/"], "granite city brawlers": [6, "/categories/granite-city-brawlers/"], "srd rank": [5, "/categories/srd-rank/"], "derby sevens": [3, "/categories/derby-sevens/"], "the big blether": [2, "/categories/the-big-blether/"], "training": [4, "/categories/training/"], "mrda": [3, "/categories/mrda/"], "prague city roller derby": [2, "/categories/prague-city-roller-derby/"], "slavic tournament": [2, "/categories/slavic-tournament/"], "warsaw hellcats": [1, "/categories/warsaw-hellcats/"], "tier 1": [1, "/categories/tier-1/"], "team middle east roller derby": [1, "/categories/team-middle-east-roller-derby/"], "abu dhabi roller derby": [2, "/categories/abu-dhabi-roller-derby/"], "mena derby": [1, "/categories/mena-derby/"], "baltic roller derby": [2, "/categories/baltic-roller-derby/"], "riga roller derby": [2, "/categories/riga-roller-derby/"], "tartu roller derby": [1, "/categories/tartu-roller-derby/"], "chicks in bowls": [3, "/categories/chicks-in-bowls/"], "wintourope": [2, "/categories/wintourope/"], "glenmore reservoir dogs": [2, "/categories/glenmore-reservoir-dogs/"], "pacific roller derby": [2, "/categories/pacific-roller-derby/"], "home game": [1, "/categories/home-game/"], "scheduling": [1, "/categories/scheduling/"], "team poland": [2, "/categories/team-poland/"], "short track roller derby": [3, "/categories/short-track-roller-derby/"], "uae all-stars roller derby": [1, "/categories/uae-all-stars-roller-derby/"], "polish roller derby": [2, "/categories/polish-roller-derby/"], "guest posts": [4, "/categories/guest-posts/"], "rankings": [5, "/categories/rankings/"], "road to playoffs": [3, "/categories/road-to-playoffs/"], "pivotstar rules": [3, "/categories/pivotstar-rules/"], "waterford viqueens": [2, "/categories/waterford-viqueens/"], "asociaci\u00f3n mexicana de roller derby": [2, "/categories/asociacion-mexicana-de-roller-derby/"], "australian men's nationals": [1, "/categories/australian-mens-nationals/"], "austrian nationals": [1, "/categories/austrian-nationals/"], "brasileir\u00e3o de roller derby": [2, "/categories/brasileirao-de-roller-derby/"], "bundesliga": [1, "/categories/bundesliga/"], "campeonato nacional de roller derby": [1, "/categories/campeonato-nacional-de-roller-derby/"], "championnat de france": [1, "/categories/championnat-de-france/"], "derby nights 4x4": [1, "/categories/derby-nights-4x4/"], "national derby fest": [1, "/categories/national-derby-fest/"], "rd.be": [1, "/categories/rdbe/"], "suomi cup": [1, "/categories/suomi-cup/"], "swedish seriespel": [1, "/categories/swedish-seriespel/"], "top 10 championships": [1, "/categories/top-10-championships/"], "torneo nacional de roller derby": [1, "/categories/torneo-nacional-de-roller-derby/"], "torneo x": [2, "/categories/torneo-x/"], "mrdwc": [2, "/categories/mrdwc/"], "mrdwc 2018": [2, "/categories/mrdwc-2018/"], "team italy mens": [1, "/categories/team-italy-mens/"], "team wales mens": [1, "/categories/team-wales-mens/"], "open": [3, "/categories/open/"], "collaboration": [1, "/categories/collaboration/"], "communication": [3, "/categories/communication/"], "consensus": [1, "/categories/consensus/"], "project management": [1, "/categories/project-management/"], "software": [1, "/categories/software/"], "tools": [1, "/categories/tools/"], "rebranding": [3, "/categories/rebranding/"], "birmingham blitz dames": [2, "/categories/birmingham-blitz-dames/"], "central city roller derby": [2, "/categories/central-city-roller-derby/"], "dock city rollers": [2, "/categories/dock-city-rollers/"], "middlesbrough roller derby": [2, "/categories/middlesbrough-roller-derby/"], "steel city roller derby": [1, "/categories/steel-city-roller-derby/"], "auld reekie roller derby": [2, "/categories/auld-reekie-roller-derby/"], "lottery funding": [1, "/categories/lottery-funding/"], "irish roller derby": [1, "/categories/irish-roller-derby/"], "surveys": [2, "/categories/surveys/"], "team gb juniors": [1, "/categories/team-gb-juniors/"], "european derby": [9, "/categories/european-derby/"], "weekly roundup": [3, "/categories/weekly-roundup/"], "jewish roller derby": [1, "/categories/jewish-roller-derby/"], "rollercon": [1, "/categories/rollercon/"], "guest articles": [4, "/categories/guest-articles/"], "continental cup": [1, "/categories/continental-cup/"], "kallio rolling rainbow": [2, "/categories/kallio-rolling-rainbow/"], "brazil": [1, "/categories/brazil/"], "brazilian roller derby": [1, "/categories/brazilian-roller-derby/"], "gray city rebels": [1, "/categories/gray-city-rebels/"], "ladies of helltown": [1, "/categories/ladies-of-helltown/"], "national tournament": [6, "/categories/national-tournament/"], "rules": [1, "/categories/rules/"], "testing": [1, "/categories/testing/"], "golden city roller derby": [1, "/categories/golden-city-roller-derby/"], "south africa": [1, "/categories/south-africa/"], "mexico": [1, "/categories/mexico/"], "derby stance": [1, "/categories/derby-stance/"], "2018 upcoming bout": [1, "/categories/2018-upcoming-bout/"], "bairn": [1, "/categories/bairn/"], "granite city": [1, "/categories/granite-city/"], "2018 season": [1, "/categories/2018-season/"], "up coming games": [1, "/categories/up-coming-games/"], "vagine regime uk": [3, "/categories/vagine-regime-uk/"], "crash test brummies": [3, "/categories/crash-test-brummies/"], "kamiquadz": [2, "/categories/kamiquadz/"], "silver city cup": [2, "/categories/silver-city-cup/"], "south wales silures": [2, "/categories/south-wales-silures/"], "tampere rollin' bros": [2, "/categories/tampere-rollin-bros/"], "mean city": [1, "/categories/mean-city/"], "painted birds roller derby": [1, "/categories/painted-birds-roller-derby/"], "p\u00e1jaros pintados roller derby": [2, "/categories/pajaros-pintados-roller-derby/"], "uruguay": [1, "/categories/uruguay/"], "colombia": [1, "/categories/colombia/"], "distrital": [1, "/categories/distrital/"], "regional occidente": [1, "/categories/regional-occidente/"], "czech republic": [1, "/categories/czech-republic/"], "hard breaking dolls": [1, "/categories/hard-breaking-dolls/"], "ingria rollers": [1, "/categories/ingria-rollers/"], "poland": [1, "/categories/poland/"], "roller derby sevens": [1, "/categories/roller-derby-sevens/"], "team czech": [2, "/categories/team-czech/"], "team poland men's roller derby": [1, "/categories/team-poland-mens-roller-derby/"], "vratislavia madchix": [1, "/categories/vratislavia-madchix/"], "events": [2, "/categories/events/"], "la boucherie de paris": [1, "/categories/la-boucherie-de-paris/"], "agm": [1, "/categories/agm/"], "ukrda directors": [1, "/categories/ukrda-directors/"], "derby directory": [1, "/categories/derby-directory/"], "coimbra": [1, "/categories/coimbra/"], "rocket dolls roller derby": [1, "/categories/rocket-dolls-roller-derby/"], "japan": [2, "/categories/japan/"], "kyoto roller derby": [1, "/categories/kyoto-roller-derby/"], "fear & lothian": [1, "/categories/fear-lothian/"], "alianza rebelde": [1, "/categories/alianza-rebelde/"], "atomic bombs roller derby": [1, "/categories/atomic-bombs-roller-derby/"], "desalmadas": [1, "/categories/desalmadas/"], "fawkes": [1, "/categories/fawkes/"], "hienas de la calle": [1, "/categories/hienas-de-la-calle/"], "mandr\u00e1goras": [1, "/categories/mandragoras/"], "mdqueens": [1, "/categories/mdqueens/"], "mor\u00f3n": [1, "/categories/moron/"], "rayo naranja": [1, "/categories/rayo-naranja/"], "sarc\u00e1sticats": [1, "/categories/sarcasticats/"], "wonderclan": [1, "/categories/wonderclan/"], "2019": [1, "/categories/2019/"], "eroc": [2, "/categories/eroc/"], "rdwc": [1, "/categories/rdwc/"], "league management": [1, "/categories/league-management/"], "trackkarma": [1, "/categories/trackkarma/"], "swede hurt": [1, "/categories/swede-hurt/"], "christmas fayre": [1, "/categories/christmas-fayre/"], "squarewheelstv": [1, "/categories/squarewheelstv/"], "cherry fury": [2, "/categories/cherry-fury/"], "ella bella bang bang": [1, "/categories/ella-bella-bang-bang/"], "refs": [1, "/categories/refs/"], "wild oates": [1, "/categories/wild-oates/"], "beach brawl": [2, "/categories/beach-brawl/"], "viewing guide": [1, "/categories/viewing-guide/"], "berlin bombshells": [1, "/categories/berlin-bombshells/"], "helsinki roller derby": [2, "/categories/helsinki-roller-derby/"], "schedule": [1, "/categories/schedule/"], "adelaide roller derby": [1, "/categories/adelaide-roller-derby/"], "copenhagen roller derby": [1, "/categories/copenhagen-roller-derby/"], "killa geishas of misawa": [1, "/categories/killa-geishas-of-misawa/"], "pirate city rollers": [1, "/categories/pirate-city-rollers/"], "lincolnshire rolling thunder": [1, "/categories/lincolnshire-rolling-thunder/"], "detroit roller derby": [1, "/categories/detroit-roller-derby/"], "european smackdown": [2, "/categories/european-smackdown/"], "stockholm roller derby": [1, "/categories/stockholm-roller-derby/"], "wftda division 1": [1, "/categories/wftda-division-1/"], "japan open roller derby tournament": [1, "/categories/japan-open-roller-derby-tournament/"], "\u30b8\u30e3\u30d1\u30f3\u30aa\u30fc\u30d7\u30f3 \u30c8\u30fc\u30ca\u30e1\u30f3\u30c8": [1, "/categories/ziyapanopun-tonamento/"], "un": [1, "/categories/un/"], "un women": [1, "/categories/un-women/"], "united nations": [1, "/categories/united-nations/"], "all stars": [1, "/categories/all-stars/"], "big o": [1, "/categories/big-o/"], "mental strength": [1, "/categories/mental-strength/"], "optimus grime": [1, "/categories/optimus-grime/"], "cib": [1, "/categories/cib/"], "skate park event": [1, "/categories/skate-park-event/"], "transgression park": [1, "/categories/transgression-park/"], "hallam hellcats roller derby": [3, "/categories/hallam-hellcats-roller-derby/"], "warriarrgs": [1, "/categories/warriarrgs/"], "hull's angels roller derby": [2, "/categories/hulls-angels-roller-derby/"], "team england roller derby": [2, "/categories/team-england-roller-derby/"], "belfast city rockets": [1, "/categories/belfast-city-rockets/"], "halifax bruising banditas": [1, "/categories/halifax-bruising-banditas/"], "arrgmageddon": [3, "/categories/arrgmageddon/"], "roller derby tenerife": [4, "/categories/roller-derby-tenerife/"], "men's european cup": [2, "/categories/mens-european-cup/"], "talk derby to me": [2, "/categories/talk-derby-to-me/"], "amusements": [1, "/categories/amusements/"], "inverclyde roller derby": [1, "/categories/inverclyde-roller-derby/"], "astros": [1, "/categories/astros/"], "texas rollergirls": [1, "/categories/texas-rollergirls/"], "european roller derby tournament": [2, "/categories/european-roller-derby-tournament/"], "the road to tbc": [1, "/categories/the-road-to-tbc/"], "ddt2016": [1, "/categories/ddt2016/"], "by the skater": [1, "/categories/by-the-skater/"], "creative commons": [1, "/categories/creative-commons/"], "for the skater": [1, "/categories/for-the-skater/"], "lgbt": [1, "/categories/lgbt/"], "lgbti": [1, "/categories/lgbti/"], "lgbtiq": [1, "/categories/lgbtiq/"], "lgbtq": [1, "/categories/lgbtq/"], "resistance roller derby": [1, "/categories/resistance-roller-derby/"], "mrdwc2016": [23, "/categories/mrdwc2016/"], "#wearefierce": [1, "/categories/wearefierce/"], "join roller derby": [1, "/categories/join-roller-derby/"], "soy division": [1, "/categories/soy-division/"], "sharks": [1, "/categories/sharks/"], "hoodoo roller derby": [1, "/categories/hoodoo-roller-derby/"], "all ireland men's roller derby": [1, "/categories/all-ireland-mens-roller-derby/"], "england men's roller derby": [1, "/categories/england-mens-roller-derby/"], "wales men's national roller derby squad": [1, "/categories/wales-mens-national-roller-derby-squad/"], "men's roller derby australia": [1, "/categories/mens-roller-derby-australia/"], "wizards of aus": [1, "/categories/wizards-of-aus/"], "listener awards": [1, "/categories/listener-awards/"], "lady trample": [1, "/categories/lady-trample/"], "scald eagle": [1, "/categories/scald-eagle/"], "merger": [1, "/categories/merger/"], "2016": [2, "/categories/2016/"], "end of year review": [1, "/categories/end-of-year-review/"], "charity": [1, "/categories/charity/"], "re:act": [1, "/categories/react/"], "west lothian roller derby": [1, "/categories/west-lothian-roller-derby/"], "belters": [1, "/categories/belters/"], "captain": [1, "/categories/captain/"], "cuckoo cadoo": [1, "/categories/cuckoo-cadoo/"], "janesaw massacre": [1, "/categories/janesaw-massacre/"], "macfarlane": [1, "/categories/macfarlane/"], "vice": [1, "/categories/vice/"], "wheely wonka": [1, "/categories/wheely-wonka/"], "northern isles": [1, "/categories/northern-isles/"], "national teams": [1, "/categories/national-teams/"], "team iceland": [1, "/categories/team-iceland/"], "team korea": [1, "/categories/team-korea/"], "team philippines": [1, "/categories/team-philippines/"]}